uio/__init__.py
uio/_version.py
uio/tasks/__init__.py
uio/tasks/reconfirming_stellar_parameters.py
uio/tests/__init__.py
uio/tests/databases.py
uio/tests/datasets.py
uio/tests/files.py
uio/tests/strings.py
uio/utility/__init__.py
uio/utility/databases/__init__.py
uio/utility/databases/lightcurves.py
uio/utility/databases/simbad.py
uio/utility/databases/tap.py
uio/utility/datasets/__init__.py
uio/utility/datasets/pandas.py
uio/utility/files/__init__.py
uio/utility/files/pickle.py
uio/utility/logs/__init__.py
uio/utility/logs/log.py
uio/utility/strings/__init__.py
uio/utility/strings/conversion.py
uio/utility/strings/extraction.py
uio_exoplanet_group-0.7.0.dist-info/LICENSE
uio_exoplanet_group-0.7.0.dist-info/METADATA
uio_exoplanet_group-0.7.0.dist-info/WHEEL
uio_exoplanet_group-0.7.0.dist-info/top_level.txt
uio_exoplanet_group-0.7.0.dist-info/RECORD
