Metadata-Version: 2.1
Name: uio-exoplanet-group
Version: 0.7.0
Summary: UiO exoplanet group tools for data processing
Home-page: https://github.com/retifrav/uio-exoplanet-group
Author: retif
Project-URL: Documentation, https://uio.decovar.dev/
Project-URL: Bug Tracker, https://github.com/retifrav/uio-exoplanet-group/issues
Project-URL: Changelog, https://github.com/retifrav/uio-exoplanet-group/blob/master/changelog.md
Keywords: tap,adql,astronomy,astrophysics,cosmology,science
Classifier: Programming Language :: Python :: 3.8
Classifier: License :: OSI Approved :: GNU General Public License v3 (GPLv3)
Classifier: Operating System :: MacOS
Classifier: Operating System :: Microsoft :: Windows
Classifier: Operating System :: POSIX :: Linux
Classifier: Topic :: Scientific/Engineering :: Astronomy
Classifier: Intended Audience :: Science/Research
Classifier: Intended Audience :: Education
Classifier: Intended Audience :: Developers
Requires-Python: >=3.8
License-File: LICENSE
Requires-Dist: pyvo
Requires-Dist: numpy
Requires-Dist: pandas
Requires-Dist: astropy
Requires-Dist: astroquery
Requires-Dist: lightkurve
Requires-Dist: matplotlib
Requires-Dist: tabulate
